{
  "header": {
    "icon": {
      "color": "orange",
      "style": "float"
    },
    "name": "מנציחים את רועי",
    "color": "default",
    "nav": [
      {
        "href": "",
        "label": "בית"
      },
      {
        "href": "friends-stories",
        "label": "חברים מספרים"
      },
      {
        "href": "from-the-media",
        "label": "מחייו"
      },
      {
        "href": "7-10",
        "label": "השבעה באוקטובר"
      },
      {
        "href": "memorial",
        "label": "הנצחה"
      },
      {
        "href": "gallery",
        "label": "תמונות"
      }
    ]
  },
  "footer": {
    "color": "default",
    "text": "כל הזכויות שמורות. אין לעשות שימוש בתכנים מאתר זה ללא אישור בכתב ממשפחתו של אל״מ רועי לוי ז״ל.",
    "image": "/uploads/public/uploads/phrase.png"
  },
  "theme": {
    "color": "blue",
    "font": "felix",
    "darkMode": "light"
  }
}